<Properties StartupConfiguration="{7F65F49A-310C-419C-A545-E4FBCDA89999}|Default">
  <MonoDevelop.Ide.ItemProperties.KundeApp2__mDataBase PreferredExecutionTarget="/Applications/Safari.app" />
  <MonoDevelop.Ide.Workbench ActiveDocument="KundeApp2_mDataBase/Controllers/Kunde_controller.cs">
    <Files>
      <File FileName="KundeApp2_mDataBase/Controllers/Kunde_controller.cs" Line="21" Column="38" />
      <File FileName="KundeApp2_mDataBase/Models/Kunde.cs" Line="8" Column="11" />
      <File FileName="KundeApp2_mDataBase/wwwroot/js/index.js" Line="35" Column="1" />
      <File FileName="KundeApp2_mDataBase/Properties/launchSettings.json" Line="23" Column="31" />
      <File FileName="KundeApp2_mDataBase/Startup.cs" Line="32" Column="10" />
      <File FileName="KundeApp2_mDataBase/Models/KundeDB.cs" Line="13" Column="49" />
    </Files>
    <Pads>
      <Pad Id="ProjectPad">
        <State name="__root__">
          <Node name="KundeApp2_mDataBase" expanded="True">
            <Node name="KundeApp2_mDataBase" expanded="True">
              <Node name="Controllers" expanded="True" />
              <Node name="Models" expanded="True" />
              <Node name="Properties" expanded="True" />
              <Node name="wwwroot" expanded="True">
                <Node name="js" expanded="True" />
              </Node>
            </Node>
          </Node>
        </State>
      </Pad>
      <Pad Id="MonoDevelop.Debugger.WatchPad">
        <State />
      </Pad>
    </Pads>
  </MonoDevelop.Ide.Workbench>
  <MonoDevelop.Ide.Workspace ActiveConfiguration="Debug" />
  <MonoDevelop.Ide.DebuggingService.Breakpoints>
    <BreakpointStore />
  </MonoDevelop.Ide.DebuggingService.Breakpoints>
  <MonoDevelop.Ide.DebuggingService.PinnedWatches />
  <MultiItemStartupConfigurations />
</Properties>